bidscramble/__init__.py
bidscramble/merge.py
bidscramble/scramble.py
bidscramble/scramble_brainvision.py
bidscramble/scramble_fif.py
bidscramble/scramble_json.py
bidscramble/scramble_nii.py
bidscramble/scramble_pseudo.py
bidscramble/scramble_stub.py
bidscramble/scramble_swap.py
bidscramble/scramble_tsv.py
bidscramble-1.0.0.dist-info/licenses/COPYING
bidscramble-1.0.0.dist-info/METADATA
bidscramble-1.0.0.dist-info/WHEEL
bidscramble-1.0.0.dist-info/entry_points.txt
bidscramble-1.0.0.dist-info/top_level.txt
bidscramble-1.0.0.dist-info/RECORD
