Metadata-Version: 2.4
Name: bidscramble
Version: 1.0.0
Summary: Generates scrambled datasets that are organized according to the Brain Imaging Data Structure (BIDS)
Author: Marcel Zwiers
Author-email: m.zwiers@donders.ru.nl
Project-URL: homepage, https://github.com/Donders-Institute/bidscramble
Project-URL: repository, https://github.com/Donders-Institute/bidscramble
Classifier: Programming Language :: Python :: 3.10
Classifier: Operating System :: OS Independent
Classifier: Intended Audience :: Science/Research
Requires-Python: >=3.10
License-File: COPYING
Requires-Dist: pandas
Requires-Dist: numpy
Requires-Dist: scipy
Requires-Dist: nibabel
Requires-Dist: pybids
Requires-Dist: bids-validator
Requires-Dist: tqdm
Requires-Dist: drmaa
Requires-Dist: brainvision
Provides-Extra: fif
Requires-Dist: mne; extra == "fif"
Provides-Extra: dev
Requires-Dist: bidscramble[fif]; extra == "dev"
Requires-Dist: tox; extra == "dev"
Requires-Dist: pytest; extra == "dev"
Requires-Dist: sphinx-rtd-theme; extra == "dev"
Requires-Dist: myst-parser; extra == "dev"
Requires-Dist: sphinx_design; extra == "dev"
Dynamic: license-file
